Workbook

Sheet Cover
B2: IT AUDIT — INITIAL REQUEST LIST (PBC TRACKER)
B3: General IT controls | SOC 2 readiness | Licensing | IT spend | Multi-entity
B5: Workbook contents
B6: 📊 Dashboard — live status across all categories (auto-updating)
B7: 📋 PBC List — all 55 audit information requests (the formal document)
B8: 🔑 Access Requests — read-only accounts and Graph API access needed
B9: 🎯 Walkthroughs — process walkthroughs to schedule (week 1-2)
B10: 🏢 Entity Scope — multi-entity scoping confirmation
B11: 🧪 Sampling & Testing — control test populations and samples
B12: 🗂 Categories — reference: 9 categories of audit requests
B14: How to use
B15: 1. Send the PBC List tab to the client IT contact as the formal audit request.
... B39: N/A — Not applicable for this engagement

Sheet Dashboard
B2: AUDIT STATUS DASHBOARD
B3: Live status — updates as the PBC List is filled in
B5: TOTAL ITEMS | C5: RECEIVED | D5: IN PROGRESS | E5: NOT STARTED | F5: % COMPLETE | G5: OUTSTANDING HIGH
B6: 55 | C6: =COUNTIF('PBC List'!H2:H56,"Received")+COUNTIF('PBC List'!H2:H56,"Reviewed") -> 0 | D6: =COUNTIF('PBC List'!H2:H56,"In Progress")+COUNTIF('PBC List'!H2:H56,"Requested") -> 0 | E6: =COUNTIF('PBC List'!H2:H56,"Not Started") -> 55 | F6: =IFERROR((COUNTIF('PBC List'!H2:H56,"Received")+COUNTIF('PBC List'!H2:H56,"Reviewed"))/(COUNTA('PBC List'!H2:H56)-COUNTIF('PBC List'!H2:H56,"N/A")),0) -> 0 | G6: =COUNTIFS('PBC List'!F2:F56,"High",'PBC List'!H2:H56,"<>Received",'PBC List'!H2:H56,"<>Reviewed",'PBC List'!H2:H56,"<>N/A") -> 31
B9: STATUS BY CATEGORY
B10: Category | C10: Total | D10: Received | E10: In Progress | F10: Not Started | G10: % Complete
B11: Governance | C11: =COUNTIF('PBC List'!B2:B56,B11) -> 7 | D11: =COUNTIFS('PBC List'!B2:B56,B11,'PBC List'!H2:H56,"Received")+COUNTIFS('PBC List'!B2:B56,B11,'PBC List'!H2:H56,"Reviewed") -> 0 | E11: =COUNTIFS('PBC List'!B2:B56,B11,'PBC List'!H2:H56,"In Progress")+COUNTIFS('PBC List'!B2:B56,B11,'PBC List'!H2:H56,"Requested") -> 0 | F11: =COUNTIFS('PBC List'!B2:B56,B11,'PBC List'!H2:H56,"Not Started") -> 7 | G11: =IFERROR(D11/(C11-COUNTIFS('PBC List'!B2:B56,B11,'PBC List'!H2:H56,"N/A")),0) -> 0
B12: Entities & Systems | C12: =COUNTIF('PBC List'!B2:B56,B12) -> 6 | D12: =COUNTIFS('PBC List'!B2:B56,B12,'PBC List'!H2:H56,"Received")+COUNTIFS('PBC List'!B2:B56,B12,'PBC List'!H2:H56,"Reviewed") -> 0 | E12: =COUNTIFS('PBC List'!B2:B56,B12,'PBC List'!H2:H56,"In Progress")+COUNTIFS('PBC List'!B2:B56,B12,'PBC List'!H2:H56,"Requested") -> 0 | F12: =COUNTIFS('PBC List'!B2:B56,B12,'PBC List'!H2:H56,"Not Started") -> 6 | G12: =IFERROR(D12/(C12-COUNTIFS('PBC List'!B2:B56,B12,'PBC List'!H2:H56,"N/A")),0) -> 0
B13: Access Management | C13: =COUNTIF('PBC List'!B2:B56,B13) -> 7 | D13: =COUNTIFS('PBC List'!B2:B56,B13,'PBC List'!H2:H56,"Received")+COUNTIFS('PBC List'!B2:B56,B13,'PBC List'!H2:H56,"Reviewed") -> 0 | E13: =COUNTIFS('PBC List'!B2:B56,B13,'PBC List'!H2:H56,"In Progress")+COUNTIFS('PBC List'!B2:B56,B13,'PBC List'!H2:H56,"Requested") -> 0 | F13: =COUNTIFS('PBC List'!B2:B56,B13,'PBC List'!H2:H56,"Not Started") -> 7 | G13: =IFERROR(D13/(C13-COUNTIFS('PBC List'!B2:B56,B13,'PBC List'!H2:H56,"N/A")),0) -> 0
B14: Change Management | C14: =COUNTIF('PBC List'!B2:B56,B14) -> 5 | D14: =COUNTIFS('PBC List'!B2:B56,B14,'PBC List'!H2:H56,"Received")+COUNTIFS('PBC List'!B2:B56,B14,'PBC List'!H2:H56,"Reviewed") -> 0 | E14: =COUNTIFS('PBC List'!B2:B56,B14,'PBC List'!H2:H56,"In Progress")+COUNTIFS('PBC List'!B2:B56,B14,'PBC List'!H2:H56,"Requested") -> 0 | F14: =COUNTIFS('PBC List'!B2:B56,B14,'PBC List'!H2:H56,"Not Started") -> 5 | G14: =IFERROR(D14/(C14-COUNTIFS('PBC List'!B2:B56,B14,'PBC List'!H2:H56,"N/A")),0) -> 0
B15: IT Operations | C15: =COUNTIF('PBC List'!B2:B56,B15) -> 7 | D15: =COUNTIFS('PBC List'!B2:B56,B15,'PBC List'!H2:H56,"Received")+COUNTIFS('PBC List'!B2:B56,B15,'PBC List'!H2:H56,"Reviewed") -> 0 | E15: =COUNTIFS('PBC List'!B2:B56,B15,'PBC List'!H2:H56,"In Progress")+COUNTIFS('PBC List'!B2:B56,B15,'PBC List'!H2:H56,"Requested") -> 0 | F15: =COUNTIFS('PBC List'!B2:B56,B15,'PBC List'!H2:H56,"Not Started") -> 7 | G15: =IFERROR(D15/(C15-COUNTIFS('PBC List'!B2:B56,B15,'PBC List'!H2:H56,"N/A")),0) -> 0
B16: Third Parties | C16: =COUNTIF('PBC List'!B2:B56,B16) -> 4 | D16: =COUNTIFS('PBC List'!B2:B56,B16,'PBC List'!H2:H56,"Received")+COUNTIFS('PBC List'!B2:B56,B16,'PBC List'!H2:H56,"Reviewed") -> 0 | E16: =COUNTIFS('PBC List'!B2:B56,B16,'PBC List'!H2:H56,"In Progress")+COUNTIFS('PBC List'!B2:B56,B16,'PBC List'!H2:H56,"Requested") -> 0 | F16: =COUNTIFS('PBC List'!B2:B56,B16,'PBC List'!H2:H56,"Not Started") -> 4 | G16: =IFERROR(D16/(C16-COUNTIFS('PBC List'!B2:B56,B16,'PBC List'!H2:H56,"N/A")),0) -> 0
B17: Licensing | C17: =COUNTIF('PBC List'!B2:B56,B17) -> 5 | D17: =COUNTIFS('PBC List'!B2:B56,B17,'PBC List'!H2:H56,"Received")+COUNTIFS('PBC List'!B2:B56,B17,'PBC List'!H2:H56,"Reviewed") -> 0 | E17: =COUNTIFS('PBC List'!B2:B56,B17,'PBC List'!H2:H56,"In Progress")+COUNTIFS('PBC List'!B2:B56,B17,'PBC List'!H2:H56,"Requested") -> 0 | F17: =COUNTIFS('PBC List'!B2:B56,B17,'PBC List'!H2:H56,"Not Started") -> 5 | G17: =IFERROR(D17/(C17-COUNTIFS('PBC List'!B2:B56,B17,'PBC List'!H2:H56,"N/A")),0) -> 0
B18: IT Spend | C18: =COUNTIF('PBC List'!B2:B56,B18) -> 7 | D18: =COUNTIFS('PBC List'!B2:B56,B18,'PBC List'!H2:H56,"Received")+COUNTIFS('PBC List'!B2:B56,B18,'PBC List'!H2:H56,"Reviewed") -> 0 | E18: =COUNTIFS('PBC List'!B2:B56,B18,'PBC List'!H2:H56,"In Progress")+COUNTIFS('PBC List'!B2:B56,B18,'PBC List'!H2:H56,"Requested") -> 0 | F18: =COUNTIFS('PBC List'!B2:B56,B18,'PBC List'!H2:H56,"Not Started") -> 7 | G18: =IFERROR(D18/(C18-COUNTIFS('PBC List'!B2:B56,B18,'PBC List'!H2:H56,"N/A")),0) -> 0
B19: SOC 2 Readiness | C19: =COUNTIF('PBC List'!B2:B56,B19) -> 5 | D19: =COUNTIFS('PBC List'!B2:B56,B19,'PBC List'!H2:H56,"Received")+COUNTIFS('PBC List'!B2:B56,B19,'PBC List'!H2:H56,"Reviewed") -> 0 | E19: =COUNTIFS('PBC List'!B2:B56,B19,'PBC List'!H2:H56,"In Progress")+COUNTIFS('PBC List'!B2:B56,B19,'PBC List'!H2:H56,"Requested") -> 0 | F19: =COUNTIFS('PBC List'!B2:B56,B19,'PBC List'!H2:H56,"Not Started") -> 5 | G19: =IFERROR(D19/(C19-COUNTIFS('PBC List'!B2:B56,B19,'PBC List'!H2:H56,"N/A")),0) -> 0
B20: Physical & Environmental | C20: =COUNTIF('PBC List'!B2:B56,B20) -> 2 | D20: =COUNTIFS('PBC List'!B2:B56,B20,'PBC List'!H2:H56,"Received")+COUNTIFS('PBC List'!B2:B56,B20,'PBC List'!H2:H56,"Reviewed") -> 0 | E20: =COUNTIFS('PBC List'!B2:B56,B20,'PBC List'!H2:H56,"In Progress")+COUNTIFS('PBC List'!B2:B56,B20,'PBC List'!H2:H56,"Requested") -> 0 | F20: =COUNTIFS('PBC List'!B2:B56,B20,'PBC List'!H2:H56,"Not Started") -> 2 | G20: =IFERROR(D20/(C20-COUNTIFS('PBC List'!B2:B56,B20,'PBC List'!H2:H56,"N/A")),0) -> 0
B21: TOTAL | C21: =SUM(C11:C20) -> 55 | D21: =SUM(D11:D20) -> 0 | E21: =SUM(E11:E20) -> 0 | F21: =SUM(F11:F20) -> 55 | G21: =IFERROR(D21/(C21-COUNTIF('PBC List'!H2:H56,"N/A")),0) -> 0
B24: STATUS BY PRIORITY
B25: Priority | C25: Total | D25: Received | E25: Outstanding
B26: High | C26: =COUNTIF('PBC List'!F2:F56,B26) -> 31 | D26: =COUNTIFS('PBC List'!F2:F56,B26,'PBC List'!H2:H56,"Received")+COUNTIFS('PBC List'!F2:F56,B26,'PBC List'!H2:H56,"Reviewed") -> 0 | E26: =C26-D26-COUNTIFS('PBC List'!F2:F56,B26,'PBC List'!H2:H56,"N/A") -> 31
B27: Medium | C27: =COUNTIF('PBC List'!F2:F56,B27) -> 15 | D27: =COUNTIFS('PBC List'!F2:F56,B27,'PBC List'!H2:H56,"Received")+COUNTIFS('PBC List'!F2:F56,B27,'PBC List'!H2:H56,"Reviewed") -> 0 | E27: =C27-D27-COUNTIFS('PBC List'!F2:F56,B27,'PBC List'!H2:H56,"N/A") -> 15
B28: Low | C28: =COUNTIF('PBC List'!F2:F56,B28) -> 1 | D28: =COUNTIFS('PBC List'!F2:F56,B28,'PBC List'!H2:H56,"Received")+COUNTIFS('PBC List'!F2:F56,B28,'PBC List'!H2:H56,"Reviewed") -> 0 | E28: =C28-D28-COUNTIFS('PBC List'!F2:F56,B28,'PBC List'!H2:H56,"N/A") -> 1
B30: Note: items rated "Medium-High" count under their respective combined priorities; treat as High for week-1 scheduling.

Sheet PBC List
A1: # | B1: Category | C1: Item Requested | D1: Why / Audit Purpose | E1: Format Expected | F1: Priority | G1: Owner (Client) | H1: Status | I1: Date Requested | J1: Date Received | K1: Notes
A2: 1 | B2: Governance | C2: IT organizational chart — all entities, with roles, reporting lines, and external vendors / MSPs / contractors involved in IT operations | D2: Understand IT structure, identify control owners, SoD at org level, surface external parties embedded in IT processes | E2: PDF / Visio | F2: High | H2: Not Started
A3: 2 | B3: Governance | C3: All IT and InfoSec policies — Acceptable Use, InfoSec, Access Control, Change Mgmt, Backup, Incident Response, Vendor Mgmt, Data Classification, BCP/DR, Password, Remote Access, Encryption, Data Retention, GenAI Use, MDM, Clean Desk | D3: Baseline for control design assessment; SOC 2 TSC mapping; check policies are current and approved | E3: PDF / Word, with version, approval date, and owner | F3: High | H3: Not Started
A4: 3 | B4: Governance | C4: IT risk assessment + risk register (current & prior year) + methodology + risk acceptance log + steering minutes referencing risk + heat map + supporting inputs (pen tests, threat intel, vuln scans, prior audits) | D4: Confirm structured, current view of IT risks; align audit scope; surface gaps where significant risks have no controls | E4: Excel + PDF | F4: High | H4: Not Started
A5: 4 | B5: Governance | C5: Prior internal/external audit reports (IT) and management responses — last 12 months (incl. internal audit, ITGC memos, prior SOC 2/ISO, regulatory inspections, pen tests, vendor licensing audits) | D5: Identify previously known findings, check remediation status, flag repeat issues | E5: PDF reports + remediation tracker | F5: Medium | H5: Not Started
A6: 5 | B6: Governance | C6: IT steering committee minutes — last 12 months, with attendees and charter | D6: Evidence of governance and oversight; tone at the top; budget/risk/incident escalation | E6: PDF | F6: Medium | H6: Not Started
A7: 6 | B7: Governance | C7: IT strategy document and roadmap (1-3 year strategy + annual roadmap) | D7: Alignment of IT direction with business strategy; planned investments and major initiatives driving change risk | E7: PDF / PowerPoint | F7: Medium | H7: Not Started
A8: 7 | B8: Governance | C8: Security awareness and training program — curriculum, completion records, phishing simulations (campaigns, click rates, repeat offenders), new-hire onboarding, role-specific training (devs, admins, finance), policy acknowledgments | D8: SOC 2 CC1.4 / CC2.2; demonstrates personnel competence and awareness; phishing/social engineering control | E8: Training platform export + materials | F8: High | H8: Not Started
A9: 8 | B9: Entities & Systems | C9: Multi-entity scoping pack — per-entity profile (legal name, country, regulatory regime, headcount, IT model, local IT, M&A); shared vs separate services matrix (identity, email, network, helpdesk, ERP, HRIS, backup, SOC); inter-entity arrangements (MSAs, allocations, data flows, cross-entity access); scoping decisions and exclusions; group structure | D9: Define audit boundary; identify intercompany IT dependencies and shared services | E9: Excel + PDF org chart | F9: High | H9: Not Started
A10: 9 | B10: Entities & Systems | C10: Application inventory per entity — name, version, owner (business + IT), criticality, hosting model, vendor, data classification, authentication, integrations, in scope for SOC 2 / financial reporting | D10: Scope in-scope systems; foundation for access, change, licensing testing | E10: Excel | F10: High | H10: Not Started
A11: 10 | B11: Entities & Systems | C11: Network architecture pack — logical + physical diagrams; cloud architecture per workload; inter-entity connectivity; perimeter; remote access; identity; data flow diagrams; IP schema; network device inventory; firewall rule base + rule review evidence; segmentation rationale; DNS architecture; certificate/PKI documentation; wireless design; change log; monitoring tools; IDS/IPS coverage | D11: Architecture, trust boundaries, segmentation; required for SOC 2 system description | E11: Visio / Lucid / PDF + Excel | F11: High | H11: Not Started
A12: 11 | B12: Entities & Systems | C12: Cloud and SaaS inventory — vendor, plan, account/tenant IDs, owner, entity, data, auth method, seats vs active users, annual cost, contract dates, SOC 2 / ISO attestations, procurement route (formal vs shadow IT) | D12: Scope cloud workloads; sub-service organizations for SOC 2; foundation for licensing/spend | E12: Excel | F12: High | H12: Not Started
A13: 12 | B13: Entities & Systems | C13: Asset inventory — servers, workstations, mobile, network devices, printers/IoT/OT; with hostname, OS, owner, location, criticality, support status; decommissioned asset list + disposal evidence; reconciliation between sources (CMDB vs Intune vs HR vs procurement) | D13: Completeness check for patch / vuln / EDR coverage testing | E13: Excel / CMDB export | F13: Medium | H13: Not Started
... A56: 55 | B56: Physical & Environmental | C56: Environmental controls — UPS, generator, fire suppression, HVAC, water detection; maintenance / inspection records (last 12 months); environmental monitoring / alerting | D56: SOC 2 Availability (only if on-prem) | E56: PDF + photos | F56: Low | H56: Not Started

Sheet Access Requests
A1: # | B1: System / Platform | C1: Access Type | D1: Role / Permissions Needed | E1: Recommended Method | F1: Justification | G1: Owner (Client) | H1: Status | I1: Provisioned Date | J1: Notes
A2: 1 | B2: Microsoft Entra ID / M365 | C2: Read-only console | D2: Global Reader | E2: Account in tenant | F2: Walkthroughs, screenshots, ad-hoc checks across multi-entity tenant | H2: Not Requested
A3: 2 | B3: Microsoft Graph API | C3: Read-only programmatic | D3: Directory.Read.All, AuditLog.Read.All, Reports.Read.All, Policy.Read.All, User.Read.All, Group.Read.All, RoleManagement.Read.All | E3: App registration with client credentials | F3: Bulk user/license/MFA/sign-in extraction across entities — essential for licensing scope | H3: Not Requested
A4: 3 | B4: Active Directory (on-prem, if any) | C4: Read-only | D4: Domain Users + read on OUs | E4: Domain account | F4: AD queries / PowerShell read commands | H4: Not Requested
A5: 4 | B5: Microsoft 365 Admin Center | C5: Read-only | D5: Global Reader | E5: Same as Entra account | F5: License assignments, mailbox stats | H5: Not Requested
A6: 5 | B6: Microsoft Purview / Compliance | C6: Read-only | D6: Compliance Data Reader / Reader | E6: Account | F6: Audit log search, DLP config, retention policies | H6: Not Requested
A7: 6 | B7: Microsoft Defender / Security portal | C7: Read-only | D7: Security Reader | E7: Account | F7: Endpoint, identity, email security posture | H7: Not Requested
A8: 7 | B8: Azure (subscriptions in scope) | C8: Read-only | D8: Reader at Mgmt Group / Subscription | E8: Account or service principal | F8: Resource inventory, RBAC review, policy compliance | H8: Not Requested
A9: 8 | B9: AWS (if applicable) | C9: Read-only | D9: ReadOnlyAccess + SecurityAudit (managed) | E9: IAM user with MFA, or SSO | F9: Cloud configuration review | H9: Not Requested
A10: 9 | B10: GCP (if applicable) | C10: Read-only | D10: Viewer + Security Reviewer | E10: Account | F10: Cloud configuration review | H10: Not Requested
A11: 10 | B11: Ticketing system (ServiceNow / Jira) | C11: Read-only | D11: Auditor / Reader role | E11: Account | F11: Pull change and incident populations, sample tickets | H11: Not Requested
A12: 11 | B12: SIEM / Log management | C12: Read-only | D12: Reader | E12: Account | F12: Verify monitoring, retention, sample alerts | H12: Not Requested
A13: 12 | B13: In-scope ERP / Finance system | C13: Read-only | D13: Auditor role with read on all modules | E13: Account | F13: GL pull for IT spend, vendor master, PO data | H13: Not Requested
... A20: 19 | B20: SAM / License mgmt tool (Flexera / Snow / etc.) | C20: Read-only | D20: Reader | E20: Account | F20: License inventory and utilization | H20: Not Requested

Sheet Walkthroughs
A1: # | B1: Process Area | C1: Key Topics | D1: Client Attendees Needed | E1: Proposed Date | F1: Duration (min) | G1: Status | H1: Notes
A2: 1 | B2: Kickoff | C2: Scope, objectives, timeline, communication, PBC list walkthrough | D2: CIO / IT Director, audit sponsor, project mgr | F2: 60 | G2: Not Scheduled
A3: 2 | B3: Entity & system scoping | C3: Entities in scope, shared services, application inventory, network architecture | D3: IT Director, Enterprise Architect | F3: 60 | G3: Not Scheduled
A4: 3 | B4: Logical access | C4: Provisioning, deprovisioning, access reviews, privileged access, MFA, JML | D4: IAM lead, HR contact | F4: 90 | G4: Not Scheduled
A5: 4 | B5: Change management | C5: Change workflow, approvals, dev/prod separation, emergency changes, source control | D5: Change manager, DevOps lead | F5: 60 | G5: Not Scheduled
A6: 5 | B6: IT operations | C6: Backups, monitoring, incident response, patching, vulnerability mgmt | D6: Ops manager, SecOps | F6: 90 | G6: Not Scheduled
A7: 6 | B7: Cloud & infrastructure | C7: M365/Azure/AWS configuration, network, segmentation, CSPM | D7: Cloud architect, network lead | F7: 60 | G7: Not Scheduled
A8: 7 | B8: Vendor & third party | C8: Vendor onboarding, SOC report review, contract management | D8: Procurement, Vendor Risk | F8: 45 | G8: Not Scheduled
A9: 8 | B9: Licensing | C9: License procurement, assignment, true-up process, SAM tooling, SaaS sprawl | D9: IT Asset Manager, Procurement | F9: 60 | G9: Not Scheduled
A10: 9 | B10: IT spend | C10: Budgeting, PO/invoice approval, intercompany allocation, capex/opex | D10: IT Finance / Controller | F10: 60 | G10: Not Scheduled
A11: 10 | B11: Physical & environmental | C11: Data center access, environmental controls (if on-prem) | D11: Facilities / IT Ops | F11: 30 | G11: Not Scheduled
A12: 11 | B12: SOC 2 readiness | C12: Trust criteria scope, system description, control matrix, gap status | D12: CISO / Compliance lead | F12: 90 | G12: Not Scheduled

Sheet Entity Scope
A1: # | B1: Legal Entity | C1: Country / Location | D1: IT Model (Centralized / Hybrid / Standalone) | E1: Key Applications | F1: Hosting (Cloud / On-Prem) | G1: Headcount | H1: In Scope (Y/N) | I1: Rationale
A2: 1
A3: 2
A4: 3
A5: 4
A6: 5
A7: 6
A8: 7
A9: 8
A10: 9
A11: 10
A12: 11
A13: 12
... A15: 14

Sheet Sampling & Testing
A1: # | B1: Control Area | C1: Control Description | D1: Population Source | E1: Population Size | F1: Sample Size | G1: Sampling Method | H1: Test Status | I1: Findings Summary
A2: 1 | B2: Access — Joiner | C2: New users provisioned with appropriate approval and access | D2: HR new hires during period | G2: Random / Judgmental | H2: Not Started
A3: 2 | B3: Access — Leaver | C3: Terminated users disabled timely (target SLA) | D3: HR terminations during period | G3: Full population if small, else random | H3: Not Started
A4: 3 | B4: Access — Mover | C4: Role changes reflected in access timely | D4: HR role change report | G4: Random | H4: Not Started
A5: 4 | B5: Access — Privileged | C5: Privileged access approved and reviewed periodically | D5: Privileged user list | G5: Full population | H5: Not Started
A6: 5 | B6: Access — Periodic Review | C6: Access review completed and exceptions remediated | D6: Review evidence per system | G6: Full population of reviews | H6: Not Started
A7: 6 | B7: Change Mgmt — Standard | C7: Changes approved, tested, deployed per process | D7: Change ticket export | G7: Random — risk-based | H7: Not Started
A8: 7 | B8: Change Mgmt — Emergency | C8: Emergency changes have post-deployment approval | D8: Emergency change subset | G8: Full population if low volume | H8: Not Started
A9: 8 | B9: Backup | C9: Backups complete successfully and restores tested | D9: Backup job logs / restore tickets | G9: Random per month | H9: Not Started
A10: 9 | B10: Incident Mgmt | C10: Incidents logged, classified, resolved within SLA | D10: Incident log | G10: Random risk-based | H10: Not Started
A11: 10 | B11: Patch Mgmt | C11: Patches deployed within SLA | D11: Patch reports / scan results | G11: Random | H11: Not Started
A12: 11 | B12: Vulnerability Mgmt | C12: Critical/high vulns remediated within SLA | D12: Scan reports | G12: All criticals + sample of highs | H12: Not Started
A13: 12 | B13: Vendor Mgmt | C13: New vendors risk-assessed and SOC reports reviewed | D13: Vendor onboarding list | G13: Random | H13: Not Started
... A17: 16 | B17: Training | C17: Required security training completed per period | D17: LMS export | G17: Random sample of staff | H17: Not Started

Sheet Categories
B2: AUDIT REQUEST CATEGORIES
B3: Reference of how the 55 PBC items are organized
B5: Category | C5: # Items | D5: Coverage
B6: Governance | C6: 7 | D6: Org structure, policies, risk, audit history, strategy, training
B7: Entities & Systems | C7: 6 | D7: Multi-entity scoping, applications, network, cloud/SaaS, assets, domains/certs
B8: Access Management | C8: 7 | D8: Identity dump, privileged users, HR reconciliation, JML, access reviews, service accounts, authentication
B9: Change Management | C9: 5 | D9: Change population, procedure, emergency changes, dev/prod segregation, code repos
B10: IT Operations | C10: 7 | D10: Backups, incidents, monitoring, patching, vulnerabilities, AV/EDR, BCP/DR
B11: Third Parties | C11: 4 | D11: Vendor inventory, assurance reports, onboarding/DD, contracts/DPAs
B12: Licensing | C12: 5 | D12: License inventory & optimization, true-ups, SaaS seats, prior audits, procurement
B13: IT Spend | C13: 7 | D13: Budget vs actual, GL detail, top vendors, PO/invoice approval, intercompany, capex/opex, shadow IT
B14: SOC 2 Readiness | C14: 5 | D14: TSC scope, control matrix, system description, risk assessment, customer commitments
B15: Physical & Environmental | C15: 2 | D15: Data center access, environmental controls (if on-prem)
B16: TOTAL | C16: 55
